{"__type": "Experiment", "name": "RandomForest_MNIST", "description": null, "experiment_type": null, "search_space": {"__type": "SearchSpace", "parameters": [{"__type": "RangeParameter", "name": "n_estimators", "parameter_type": {"__type": "ParameterType", "name": "INT"}, "lower": 2, "upper": 200, "log_scale": false, "digits": null}, {"__type": "RangeParameter", "name": "max_depth", "parameter_type": {"__type": "ParameterType", "name": "INT"}, "lower": 1, "upper": 10, "log_scale": false, "digits": null}, {"__type": "RangeParameter", "name": "min_samples_leaf", "parameter_type": {"__type": "ParameterType", "name": "INT"}, "lower": 1, "upper": 20, "log_scale": false, "digits": null}], "parameter_constraints": []}, "optimization_config": {"__type": "OptimizationConfig", "objective": {"__type": "Objective", "metric": {"name": "accuracy", "__type": "Metric"}, "minimize": false}, "outcome_constraints": []}, "tracking_metrics": [], "runner": null, "status_quo": null, "time_created": {"__type": "datetime", "value": "2019-05-16 14:14:25.443084"}, "trials": {"0": {"__type": "Trial", "index": 0, "trial_type": null, "status": {"__type": "TrialStatus", "name": "COMPLETED"}, "time_created": {"__type": "datetime", "value": "2019-05-16 14:14:25.462471"}, "time_completed": null, "time_staged": null, "time_run_started": null, "abandoned_reason": null, "run_metadata": {}, "generator_run": {"__type": "GeneratorRun", "arms": [{"__type": "Arm", "parameters": {"n_estimators": 187, "max_depth": 8, "min_samples_leaf": 14}, "name": "0_0"}], "weights": [1.0], "optimization_config": null, "search_space": {"__type": "SearchSpace", "parameters": [{"__type": "RangeParameter", "name": "n_estimators", "parameter_type": {"__type": "ParameterType", "name": "FLOAT"}, "lower": 0.0, "upper": 1.0, "log_scale": false, "digits": null}, {"__type": "RangeParameter", "name": "max_depth", "parameter_type": {"__type": "ParameterType", "name": "FLOAT"}, "lower": 0.0, "upper": 1.0, "log_scale": false, "digits": null}, {"__type": "RangeParameter", "name": "min_samples_leaf", "parameter_type": {"__type": "ParameterType", "name": "FLOAT"}, "lower": 0.0, "upper": 1.0, "log_scale": false, "digits": null}], "parameter_constraints": []}, "time_created": {"__type": "datetime", "value": "2019-05-16 14:14:25.462391"}, "model_predictions": null, "best_arm_predictions": null, "generator_run_type": null, "index": 0, "fit_time": 0.00016641616821289062, "gen_time": 0.0007042884826660156}, "runner": null, "num_arms_created": 1}, "1": {"__type": "Trial", "index": 1, "trial_type": null, "status": {"__type": "TrialStatus", "name": "COMPLETED"}, "time_created": {"__type": "datetime", "value": "2019-05-16 14:14:25.699014"}, "time_completed": null, "time_staged": null, "time_run_started": null, "abandoned_reason": null, "run_metadata": {}, "generator_run": {"__type": "GeneratorRun", "arms": [{"__type": "Arm", "parameters": {"n_estimators": 135, "max_depth": 4, "min_samples_leaf": 19}, "name": "1_0"}], "weights": [1.0], "optimization_config": null, "search_space": {"__type": "SearchSpace", "parameters": [{"__type": "RangeParameter", "name": "n_estimators", "parameter_type": {"__type": "ParameterType", "name": "FLOAT"}, "lower": 0.0, "upper": 1.0, "log_scale": false, "digits": null}, {"__type": "RangeParameter", "name": "max_depth", "parameter_type": {"__type": "ParameterType", "name": "FLOAT"}, "lower": 0.0, "upper": 1.0, "log_scale": false, "digits": null}, {"__type": "RangeParameter", "name": "min_samples_leaf", "parameter_type": {"__type": "ParameterType", "name": "FLOAT"}, "lower": 0.0, "upper": 1.0, "log_scale": false, "digits": null}], "parameter_constraints": []}, "time_created": {"__type": "datetime", "value": "2019-05-16 14:14:25.698945"}, "model_predictions": null, "best_arm_predictions": null, "generator_run_type": null, "index": 0, "fit_time": 0.0, "gen_time": 0.00031495094299316406}, "runner": null, "num_arms_created": 1}, "2": {"__type": "Trial", "index": 2, "trial_type": null, "status": {"__type": "TrialStatus", "name": "COMPLETED"}, "time_created": {"__type": "datetime", "value": "2019-05-16 14:14:25.842559"}, "time_completed": null, "time_staged": null, "time_run_started": null, "abandoned_reason": null, "run_metadata": {}, "generator_run": {"__type": "GeneratorRun", "arms": [{"__type": "Arm", "parameters": {"n_estimators": 61, "max_depth": 7, "min_samples_leaf": 2}, "name": "2_0"}], "weights": [1.0], "optimization_config": null, "search_space": {"__type": "SearchSpace", "parameters": [{"__type": "RangeParameter", "name": "n_estimators", "parameter_type": {"__type": "ParameterType", "name": "FLOAT"}, "lower": 0.0, "upper": 1.0, "log_scale": false, "digits": null}, {"__type": "RangeParameter", "name": "max_depth", "parameter_type": {"__type": "ParameterType", "name": "FLOAT"}, "lower": 0.0, "upper": 1.0, "log_scale": false, "digits": null}, {"__type": "RangeParameter", "name": "min_samples_leaf", "parameter_type": {"__type": "ParameterType", "name": "FLOAT"}, "lower": 0.0, "upper": 1.0, "log_scale": false, "digits": null}], "parameter_constraints": []}, "time_created": {"__type": "datetime", "value": "2019-05-16 14:14:25.842491"}, "model_predictions": null, "best_arm_predictions": null, "generator_run_type": null, "index": 0, "fit_time": 0.0, "gen_time": 0.0003159046173095703}, "runner": null, "num_arms_created": 1}, "3": {"__type": "Trial", "index": 3, "trial_type": null, "status": {"__type": "TrialStatus", "name": "COMPLETED"}, "time_created": {"__type": "datetime", "value": "2019-05-16 14:14:25.938368"}, "time_completed": null, "time_staged": null, "time_run_started": null, "abandoned_reason": null, "run_metadata": {}, "generator_run": {"__type": "GeneratorRun", "arms": [{"__type": "Arm", "parameters": {"n_estimators": 92, "max_depth": 4, "min_samples_leaf": 12}, "name": "3_0"}], "weights": [1.0], "optimization_config": null, "search_space": {"__type": "SearchSpace", "parameters": [{"__type": "RangeParameter", "name": "n_estimators", "parameter_type": {"__type": "ParameterType", "name": "FLOAT"}, "lower": 0.0, "upper": 1.0, "log_scale": false, "digits": null}, {"__type": "RangeParameter", "name": "max_depth", "parameter_type": {"__type": "ParameterType", "name": "FLOAT"}, "lower": 0.0, "upper": 1.0, "log_scale": false, "digits": null}, {"__type": "RangeParameter", "name": "min_samples_leaf", "parameter_type": {"__type": "ParameterType", "name": "FLOAT"}, "lower": 0.0, "upper": 1.0, "log_scale": false, "digits": null}], "parameter_constraints": []}, "time_created": {"__type": "datetime", "value": "2019-05-16 14:14:25.938300"}, "model_predictions": null, "best_arm_predictions": null, "generator_run_type": null, "index": 0, "fit_time": 0.0, "gen_time": 0.0003032684326171875}, "runner": null, "num_arms_created": 1}, "4": {"__type": "Trial", "index": 4, "trial_type": null, "status": {"__type": "TrialStatus", "name": "COMPLETED"}, "time_created": {"__type": "datetime", "value": "2019-05-16 14:14:26.039858"}, "time_completed": null, "time_staged": null, "time_run_started": null, "abandoned_reason": null, "run_metadata": {}, "generator_run": {"__type": "GeneratorRun", "arms": [{"__type": "Arm", "parameters": {"n_estimators": 117, "max_depth": 6, "min_samples_leaf": 10}, "name": "4_0"}], "weights": [1.0], "optimization_config": null, "search_space": {"__type": "SearchSpace", "parameters": [{"__type": "RangeParameter", "name": "n_estimators", "parameter_type": {"__type": "ParameterType", "name": "FLOAT"}, "lower": 0.0, "upper": 1.0, "log_scale": false, "digits": null}, {"__type": "RangeParameter", "name": "max_depth", "parameter_type": {"__type": "ParameterType", "name": "FLOAT"}, "lower": 0.0, "upper": 1.0, "log_scale": false, "digits": null}, {"__type": "RangeParameter", "name": "min_samples_leaf", "parameter_type": {"__type": "ParameterType", "name": "FLOAT"}, "lower": 0.0, "upper": 1.0, "log_scale": false, "digits": null}], "parameter_constraints": []}, "time_created": {"__type": "datetime", "value": "2019-05-16 14:14:26.039792"}, "model_predictions": null, "best_arm_predictions": null, "generator_run_type": null, "index": 0, "fit_time": 0.0, "gen_time": 0.00029206275939941406}, "runner": null, "num_arms_created": 1}, "5": {"__type": "Trial", "index": 5, "trial_type": null, "status": {"__type": "TrialStatus", "name": "COMPLETED"}, "time_created": {"__type": "datetime", "value": "2019-05-16 14:14:26.872494"}, "time_completed": null, "time_staged": null, "time_run_started": null, "abandoned_reason": null, "run_metadata": {}, "generator_run": {"__type": "GeneratorRun", "arms": [{"__type": "Arm", "parameters": {"n_estimators": 100, "max_depth": 3, "min_samples_leaf": 16}, "name": "5_0"}], "weights": [1.0], "optimization_config": {"__type": "OptimizationConfig", "objective": {"__type": "Objective", "metric": {"name": "accuracy", "__type": "Metric"}, "minimize": false}, "outcome_constraints": []}, "search_space": {"__type": "SearchSpace", "parameters": [{"__type": "RangeParameter", "name": "n_estimators", "parameter_type": {"__type": "ParameterType", "name": "FLOAT"}, "lower": 0.0, "upper": 1.0, "log_scale": false, "digits": null}, {"__type": "RangeParameter", "name": "max_depth", "parameter_type": {"__type": "ParameterType", "name": "FLOAT"}, "lower": 0.0, "upper": 1.0, "log_scale": false, "digits": null}, {"__type": "RangeParameter", "name": "min_samples_leaf", "parameter_type": {"__type": "ParameterType", "name": "FLOAT"}, "lower": 0.0, "upper": 1.0, "log_scale": false, "digits": null}], "parameter_constraints": []}, "time_created": {"__type": "datetime", "value": "2019-05-16 14:14:26.872375"}, "model_predictions": [{"accuracy": [0.9439109482456558]}, {"accuracy": {"accuracy": [0.01471158575840341]}}], "best_arm_predictions": [{"__type": "Arm", "parameters": {"n_estimators": 135, "max_depth": 4, "min_samples_leaf": 19}, "name": "1_0"}, [{"accuracy": 0.9263213054889883}, {"accuracy": {"accuracy": 3.506443214880902e-09}}]], "generator_run_type": null, "index": 0, "fit_time": 0.08217573165893555, "gen_time": 0.5978050231933594}, "runner": null, "num_arms_created": 1}, "6": {"__type": "Trial", "index": 6, "trial_type": null, "status": {"__type": "TrialStatus", "name": "COMPLETED"}, "time_created": {"__type": "datetime", "value": "2019-05-16 14:14:28.236036"}, "time_completed": null, "time_staged": null, "time_run_started": null, "abandoned_reason": null, "run_metadata": {}, "generator_run": {"__type": "GeneratorRun", "arms": [{"__type": "Arm", "parameters": {"n_estimators": 84, "max_depth": 2, "min_samples_leaf": 17}, "name": "6_0"}], "weights": [1.0], "optimization_config": {"__type": "OptimizationConfig", "objective": {"__type": "Objective", "metric": {"name": "accuracy", "__type": "Metric"}, "minimize": false}, "outcome_constraints": []}, "search_space": {"__type": "SearchSpace", "parameters": [{"__type": "RangeParameter", "name": "n_estimators", "parameter_type": {"__type": "ParameterType", "name": "FLOAT"}, "lower": 0.0, "upper": 1.0, "log_scale": false, "digits": null}, {"__type": "RangeParameter", "name": "max_depth", "parameter_type": {"__type": "ParameterType", "name": "FLOAT"}, "lower": 0.0, "upper": 1.0, "log_scale": false, "digits": null}, {"__type": "RangeParameter", "name": "min_samples_leaf", "parameter_type": {"__type": "ParameterType", "name": "FLOAT"}, "lower": 0.0, "upper": 1.0, "log_scale": false, "digits": null}], "parameter_constraints": []}, "time_created": {"__type": "datetime", "value": "2019-05-16 14:14:28.235909"}, "model_predictions": [{"accuracy": [1.170816616410903]}, {"accuracy": {"accuracy": [0.01437423810297363]}}], "best_arm_predictions": [{"__type": "Arm", "parameters": {"n_estimators": 100, "max_depth": 3, "min_samples_leaf": 16}, "name": "5_0"}, [{"accuracy": 1.1688601491686872}, {"accuracy": {"accuracy": 3.5064429268037573e-09}}]], "generator_run_type": null, "index": 0, "fit_time": 0.0327913761138916, "gen_time": 1.1912105083465576}, "runner": null, "num_arms_created": 1}, "7": {"__type": "Trial", "index": 7, "trial_type": null, "status": {"__type": "TrialStatus", "name": "COMPLETED"}, "time_created": {"__type": "datetime", "value": "2019-05-16 14:14:29.346412"}, "time_completed": null, "time_staged": null, "time_run_started": null, "abandoned_reason": null, "run_metadata": {}, "generator_run": {"__type": "GeneratorRun", "arms": [{"__type": "Arm", "parameters": {"n_estimators": 67, "max_depth": 1, "min_samples_leaf": 18}, "name": "7_0"}], "weights": [1.0], "optimization_config": {"__type": "OptimizationConfig", "objective": {"__type": "Objective", "metric": {"name": "accuracy", "__type": "Metric"}, "minimize": false}, "outcome_constraints": []}, "search_space": {"__type": "SearchSpace", "parameters": [{"__type": "RangeParameter", "name": "n_estimators", "parameter_type": {"__type": "ParameterType", "name": "FLOAT"}, "lower": 0.0, "upper": 1.0, "log_scale": false, "digits": null}, {"__type": "RangeParameter", "name": "max_depth", "parameter_type": {"__type": "ParameterType", "name": "FLOAT"}, "lower": 0.0, "upper": 1.0, "log_scale": false, "digits": null}, {"__type": "RangeParameter", "name": "min_samples_leaf", "parameter_type": {"__type": "ParameterType", "name": "FLOAT"}, "lower": 0.0, "upper": 1.0, "log_scale": false, "digits": null}], "parameter_constraints": []}, "time_created": {"__type": "datetime", "value": "2019-05-16 14:14:29.346240"}, "model_predictions": [{"accuracy": [1.6447850073183612]}, {"accuracy": {"accuracy": [0.02350297065599466]}}], "best_arm_predictions": [{"__type": "Arm", "parameters": {"n_estimators": 84, "max_depth": 2, "min_samples_leaf": 17}, "name": "6_0"}, [{"accuracy": 1.545055578229651}, {"accuracy": {"accuracy": 3.506443207095033e-09}}]], "generator_run_type": null, "index": 0, "fit_time": 0.04798746109008789, "gen_time": 0.9402673244476318}, "runner": null, "num_arms_created": 1}, "8": {"__type": "Trial", "index": 8, "trial_type": null, "status": {"__type": "TrialStatus", "name": "COMPLETED"}, "time_created": {"__type": "datetime", "value": "2019-05-16 14:14:30.273657"}, "time_completed": null, "time_staged": null, "time_run_started": null, "abandoned_reason": null, "run_metadata": {}, "generator_run": {"__type": "GeneratorRun", "arms": [{"__type": "Arm", "parameters": {"n_estimators": 29, "max_depth": 1, "min_samples_leaf": 20}, "name": "8_0"}], "weights": [1.0], "optimization_config": {"__type": "OptimizationConfig", "objective": {"__type": "Objective", "metric": {"name": "accuracy", "__type": "Metric"}, "minimize": false}, "outcome_constraints": []}, "search_space": {"__type": "SearchSpace", "parameters": [{"__type": "RangeParameter", "name": "n_estimators", "parameter_type": {"__type": "ParameterType", "name": "FLOAT"}, "lower": 0.0, "upper": 1.0, "log_scale": false, "digits": null}, {"__type": "RangeParameter", "name": "max_depth", "parameter_type": {"__type": "ParameterType", "name": "FLOAT"}, "lower": 0.0, "upper": 1.0, "log_scale": false, "digits": null}, {"__type": "RangeParameter", "name": "min_samples_leaf", "parameter_type": {"__type": "ParameterType", "name": "FLOAT"}, "lower": 0.0, "upper": 1.0, "log_scale": false, "digits": null}], "parameter_constraints": []}, "time_created": {"__type": "datetime", "value": "2019-05-16 14:14:30.273496"}, "model_predictions": [{"accuracy": [1.9445278166831115]}, {"accuracy": {"accuracy": [0.04070608662307852]}}], "best_arm_predictions": [{"__type": "Arm", "parameters": {"n_estimators": 67, "max_depth": 1, "min_samples_leaf": 18}, "name": "7_0"}, [{"accuracy": 1.9056997299561864}, {"accuracy": {"accuracy": 3.5064426153690064e-09}}]], "generator_run_type": null, "index": 0, "fit_time": 0.04525446891784668, "gen_time": 0.7995145320892334}, "runner": null, "num_arms_created": 1}, "9": {"__type": "Trial", "index": 9, "trial_type": null, "status": {"__type": "TrialStatus", "name": "COMPLETED"}, "time_created": {"__type": "datetime", "value": "2019-05-16 14:14:31.530491"}, "time_completed": null, "time_staged": null, "time_run_started": null, "abandoned_reason": null, "run_metadata": {}, "generator_run": {"__type": "GeneratorRun", "arms": [{"__type": "Arm", "parameters": {"n_estimators": 28, "max_depth": 1, "min_samples_leaf": 16}, "name": "9_0"}], "weights": [1.0], "optimization_config": {"__type": "OptimizationConfig", "objective": {"__type": "Objective", "metric": {"name": "accuracy", "__type": "Metric"}, "minimize": false}, "outcome_constraints": []}, "search_space": {"__type": "SearchSpace", "parameters": [{"__type": "RangeParameter", "name": "n_estimators", "parameter_type": {"__type": "ParameterType", "name": "FLOAT"}, "lower": 0.0, "upper": 1.0, "log_scale": false, "digits": null}, {"__type": "RangeParameter", "name": "max_depth", "parameter_type": {"__type": "ParameterType", "name": "FLOAT"}, "lower": 0.0, "upper": 1.0, "log_scale": false, "digits": null}, {"__type": "RangeParameter", "name": "min_samples_leaf", "parameter_type": {"__type": "ParameterType", "name": "FLOAT"}, "lower": 0.0, "upper": 1.0, "log_scale": false, "digits": null}], "parameter_constraints": []}, "time_created": {"__type": "datetime", "value": "2019-05-16 14:14:31.530362"}, "model_predictions": [{"accuracy": [1.868309421123907]}, {"accuracy": {"accuracy": [0.02244805594145975]}}], "best_arm_predictions": [{"__type": "Arm", "parameters": {"n_estimators": 29, "max_depth": 1, "min_samples_leaf": 20}, "name": "8_0"}, [{"accuracy": 1.9245392149395768}, {"accuracy": {"accuracy": 3.506443175951558e-09}}]], "generator_run_type": null, "index": 0, "fit_time": 0.05712389945983887, "gen_time": 1.1380033493041992}, "runner": null, "num_arms_created": 1}, "10": {"__type": "Trial", "index": 10, "trial_type": null, "status": {"__type": "TrialStatus", "name": "COMPLETED"}, "time_created": {"__type": "datetime", "value": "2019-05-16 14:14:32.144037"}, "time_completed": null, "time_staged": null, "time_run_started": null, "abandoned_reason": null, "run_metadata": {}, "generator_run": {"__type": "GeneratorRun", "arms": [{"__type": "Arm", "parameters": {"n_estimators": 41, "max_depth": 1, "min_samples_leaf": 18}, "name": "10_0"}], "weights": [1.0], "optimization_config": {"__type": "OptimizationConfig", "objective": {"__type": "Objective", "metric": {"name": "accuracy", "__type": "Metric"}, "minimize": false}, "outcome_constraints": []}, "search_space": {"__type": "SearchSpace", "parameters": [{"__type": "RangeParameter", "name": "n_estimators", "parameter_type": {"__type": "ParameterType", "name": "FLOAT"}, "lower": 0.0, "upper": 1.0, "log_scale": false, "digits": null}, {"__type": "RangeParameter", "name": "max_depth", "parameter_type": {"__type": "ParameterType", "name": "FLOAT"}, "lower": 0.0, "upper": 1.0, "log_scale": false, "digits": null}, {"__type": "RangeParameter", "name": "min_samples_leaf", "parameter_type": {"__type": "ParameterType", "name": "FLOAT"}, "lower": 0.0, "upper": 1.0, "log_scale": false, "digits": null}], "parameter_constraints": []}, "time_created": {"__type": "datetime", "value": "2019-05-16 14:14:32.143912"}, "model_predictions": [{"accuracy": [1.947028641301129]}, {"accuracy": {"accuracy": [0.0004192607069542178]}}], "best_arm_predictions": [{"__type": "Arm", "parameters": {"n_estimators": 29, "max_depth": 1, "min_samples_leaf": 20}, "name": "8_0"}, [{"accuracy": 1.9245392213668373}, {"accuracy": {"accuracy": 3.506442864516807e-09}}]], "generator_run_type": null, "index": 0, "fit_time": 0.04134082794189453, "gen_time": 0.518549919128418}, "runner": null, "num_arms_created": 1}, "11": {"__type": "Trial", "index": 11, "trial_type": null, "status": {"__type": "TrialStatus", "name": "COMPLETED"}, "time_created": {"__type": "datetime", "value": "2019-05-16 14:14:32.716825"}, "time_completed": null, "time_staged": null, "time_run_started": null, "abandoned_reason": null, "run_metadata": {}, "generator_run": {"__type": "GeneratorRun", "arms": [{"__type": "Arm", "parameters": {"n_estimators": 2, "max_depth": 1, "min_samples_leaf": 3}, "name": "11_0"}], "weights": [1.0], "optimization_config": {"__type": "OptimizationConfig", "objective": {"__type": "Objective", "metric": {"name": "accuracy", "__type": "Metric"}, "minimize": false}, "outcome_constraints": []}, "search_space": {"__type": "SearchSpace", "parameters": [{"__type": "RangeParameter", "name": "n_estimators", "parameter_type": {"__type": "ParameterType", "name": "FLOAT"}, "lower": 0.0, "upper": 1.0, "log_scale": false, "digits": null}, {"__type": "RangeParameter", "name": "max_depth", "parameter_type": {"__type": "ParameterType", "name": "FLOAT"}, "lower": 0.0, "upper": 1.0, "log_scale": false, "digits": null}, {"__type": "RangeParameter", "name": "min_samples_leaf", "parameter_type": {"__type": "ParameterType", "name": "FLOAT"}, "lower": 0.0, "upper": 1.0, "log_scale": false, "digits": null}], "parameter_constraints": []}, "time_created": {"__type": "datetime", "value": "2019-05-16 14:14:32.716697"}, "model_predictions": [{"accuracy": [1.6463610893318466]}, {"accuracy": {"accuracy": [0.05793767562112038]}}], "best_arm_predictions": [{"__type": "Arm", "parameters": {"n_estimators": 29, "max_depth": 1, "min_samples_leaf": 20}, "name": "8_0"}, [{"accuracy": 1.9245391384524375}, {"accuracy": {"accuracy": 3.506432805174351e-09}}]], "generator_run_type": null, "index": 0, "fit_time": 0.043067216873168945, "gen_time": 0.4685509204864502}, "runner": null, "num_arms_created": 1}, "12": {"__type": "Trial", "index": 12, "trial_type": null, "status": {"__type": "TrialStatus", "name": "COMPLETED"}, "time_created": {"__type": "datetime", "value": "2019-05-16 14:14:33.229639"}, "time_completed": null, "time_staged": null, "time_run_started": null, "abandoned_reason": null, "run_metadata": {}, "generator_run": {"__type": "GeneratorRun", "arms": [{"__type": "Arm", "parameters": {"n_estimators": 69, "max_depth": 1, "min_samples_leaf": 1}, "name": "12_0"}], "weights": [1.0], "optimization_config": {"__type": "OptimizationConfig", "objective": {"__type": "Objective", "metric": {"name": "accuracy", "__type": "Metric"}, "minimize": false}, "outcome_constraints": []}, "search_space": {"__type": "SearchSpace", "parameters": [{"__type": "RangeParameter", "name": "n_estimators", "parameter_type": {"__type": "ParameterType", "name": "FLOAT"}, "lower": 0.0, "upper": 1.0, "log_scale": false, "digits": null}, {"__type": "RangeParameter", "name": "max_depth", "parameter_type": {"__type": "ParameterType", "name": "FLOAT"}, "lower": 0.0, "upper": 1.0, "log_scale": false, "digits": null}, {"__type": "RangeParameter", "name": "min_samples_leaf", "parameter_type": {"__type": "ParameterType", "name": "FLOAT"}, "lower": 0.0, "upper": 1.0, "log_scale": false, "digits": null}], "parameter_constraints": []}, "time_created": {"__type": "datetime", "value": "2019-05-16 14:14:33.229510"}, "model_predictions": [{"accuracy": [1.8563549886322457]}, {"accuracy": {"accuracy": [0.029277534610423032]}}], "best_arm_predictions": [{"__type": "Arm", "parameters": {"n_estimators": 2, "max_depth": 1, "min_samples_leaf": 3}, "name": "11_0"}, [{"accuracy": 1.9705277544502542}, {"accuracy": {"accuracy": 3.506443487386309e-09}}]], "generator_run_type": null, "index": 0, "fit_time": 0.04819774627685547, "gen_time": 0.4396786689758301}, "runner": null, "num_arms_created": 1}, "13": {"__type": "Trial", "index": 13, "trial_type": null, "status": {"__type": "TrialStatus", "name": "COMPLETED"}, "time_created": {"__type": "datetime", "value": "2019-05-16 14:14:33.726418"}, "time_completed": null, "time_staged": null, "time_run_started": null, "abandoned_reason": null, "run_metadata": {}, "generator_run": {"__type": "GeneratorRun", "arms": [{"__type": "Arm", "parameters": {"n_estimators": 31, "max_depth": 1, "min_samples_leaf": 5}, "name": "13_0"}], "weights": [1.0], "optimization_config": {"__type": "OptimizationConfig", "objective": {"__type": "Objective", "metric": {"name": "accuracy", "__type": "Metric"}, "minimize": false}, "outcome_constraints": []}, "search_space": {"__type": "SearchSpace", "parameters": [{"__type": "RangeParameter", "name": "n_estimators", "parameter_type": {"__type": "ParameterType", "name": "FLOAT"}, "lower": 0.0, "upper": 1.0, "log_scale": false, "digits": null}, {"__type": "RangeParameter", "name": "max_depth", "parameter_type": {"__type": "ParameterType", "name": "FLOAT"}, "lower": 0.0, "upper": 1.0, "log_scale": false, "digits": null}, {"__type": "RangeParameter", "name": "min_samples_leaf", "parameter_type": {"__type": "ParameterType", "name": "FLOAT"}, "lower": 0.0, "upper": 1.0, "log_scale": false, "digits": null}], "parameter_constraints": []}, "time_created": {"__type": "datetime", "value": "2019-05-16 14:14:33.726298"}, "model_predictions": [{"accuracy": [1.962004891356108]}, {"accuracy": {"accuracy": [0.0014158721431822912]}}], "best_arm_predictions": [{"__type": "Arm", "parameters": {"n_estimators": 2, "max_depth": 1, "min_samples_leaf": 3}, "name": "11_0"}, [{"accuracy": 1.970527758629656}, {"accuracy": {"accuracy": 3.5064426465124814e-09}}]], "generator_run_type": null, "index": 0, "fit_time": 0.04317140579223633, "gen_time": 0.3701021671295166}, "runner": null, "num_arms_created": 1}, "14": {"__type": "Trial", "index": 14, "trial_type": null, "status": {"__type": "TrialStatus", "name": "COMPLETED"}, "time_created": {"__type": "datetime", "value": "2019-05-16 14:14:34.142514"}, "time_completed": null, "time_staged": null, "time_run_started": null, "abandoned_reason": null, "run_metadata": {}, "generator_run": {"__type": "GeneratorRun", "arms": [{"__type": "Arm", "parameters": {"n_estimators": 2, "max_depth": 1, "min_samples_leaf": 1}, "name": "14_0"}], "weights": [1.0], "optimization_config": {"__type": "OptimizationConfig", "objective": {"__type": "Objective", "metric": {"name": "accuracy", "__type": "Metric"}, "minimize": false}, "outcome_constraints": []}, "search_space": {"__type": "SearchSpace", "parameters": [{"__type": "RangeParameter", "name": "n_estimators", "parameter_type": {"__type": "ParameterType", "name": "FLOAT"}, "lower": 0.0, "upper": 1.0, "log_scale": false, "digits": null}, {"__type": "RangeParameter", "name": "max_depth", "parameter_type": {"__type": "ParameterType", "name": "FLOAT"}, "lower": 0.0, "upper": 1.0, "log_scale": false, "digits": null}, {"__type": "RangeParameter", "name": "min_samples_leaf", "parameter_type": {"__type": "ParameterType", "name": "FLOAT"}, "lower": 0.0, "upper": 1.0, "log_scale": false, "digits": null}], "parameter_constraints": []}, "time_created": {"__type": "datetime", "value": "2019-05-16 14:14:34.142385"}, "model_predictions": [{"accuracy": [1.9941248446220867]}, {"accuracy": {"accuracy": [0.00039181902495842526]}}], "best_arm_predictions": [{"__type": "Arm", "parameters": {"n_estimators": 2, "max_depth": 1, "min_samples_leaf": 3}, "name": "11_0"}, [{"accuracy": 1.9705277057708448}, {"accuracy": {"accuracy": 3.5064404976126996e-09}}]], "generator_run_type": null, "index": 0, "fit_time": 0.04257011413574219, "gen_time": 0.3234884738922119}, "runner": null, "num_arms_created": 1}}, "is_test": false, "data_by_trial": {"0": {"__type": "OrderedDict", "value": [[1558026865689, {"__type": "Data", "df": {"__type": "DataFrame", "value": "{\"arm_name\":{\"0\":\"0_0\"},\"mean\":{\"0\":0.5915595243},\"metric_name\":{\"0\":\"accuracy\"},\"sem\":{\"0\":0.0},\"trial_index\":{\"0\":0}}"}, "description": null}]]}, "1": {"__type": "OrderedDict", "value": [[1558026865830, {"__type": "Data", "df": {"__type": "DataFrame", "value": "{\"arm_name\":{\"0\":\"1_0\"},\"mean\":{\"0\":0.9263213173},\"metric_name\":{\"0\":\"accuracy\"},\"sem\":{\"0\":0.0},\"trial_index\":{\"0\":1}}"}, "description": null}]]}, "2": {"__type": "OrderedDict", "value": [[1558026865926, {"__type": "Data", "df": {"__type": "DataFrame", "value": "{\"arm_name\":{\"0\":\"2_0\"},\"mean\":{\"0\":0.4587360491},\"metric_name\":{\"0\":\"accuracy\"},\"sem\":{\"0\":0.0},\"trial_index\":{\"0\":2}}"}, "description": null}]]}, "3": {"__type": "OrderedDict", "value": [[1558026866028, {"__type": "Data", "df": {"__type": "DataFrame", "value": "{\"arm_name\":{\"0\":\"3_0\"},\"mean\":{\"0\":0.9098707784},\"metric_name\":{\"0\":\"accuracy\"},\"sem\":{\"0\":0.0},\"trial_index\":{\"0\":3}}"}, "description": null}]]}, "4": {"__type": "OrderedDict", "value": [[1558026866180, {"__type": "Data", "df": {"__type": "DataFrame", "value": "{\"arm_name\":{\"0\":\"4_0\"},\"mean\":{\"0\":0.5993645315},\"metric_name\":{\"0\":\"accuracy\"},\"sem\":{\"0\":0.0},\"trial_index\":{\"0\":4}}"}, "description": null}]]}, "5": {"__type": "OrderedDict", "value": [[1558026866995, {"__type": "Data", "df": {"__type": "DataFrame", "value": "{\"arm_name\":{\"0\":\"5_0\"},\"mean\":{\"0\":1.1688601848},\"metric_name\":{\"0\":\"accuracy\"},\"sem\":{\"0\":0.0},\"trial_index\":{\"0\":5}}"}, "description": null}]]}, "6": {"__type": "OrderedDict", "value": [[1558026868339, {"__type": "Data", "df": {"__type": "DataFrame", "value": "{\"arm_name\":{\"0\":\"6_0\"},\"mean\":{\"0\":1.5450556176},\"metric_name\":{\"0\":\"accuracy\"},\"sem\":{\"0\":0.0},\"trial_index\":{\"0\":6}}"}, "description": null}]]}, "7": {"__type": "OrderedDict", "value": [[1558026869412, {"__type": "Data", "df": {"__type": "DataFrame", "value": "{\"arm_name\":{\"0\":\"7_0\"},\"mean\":{\"0\":1.9056997675},\"metric_name\":{\"0\":\"accuracy\"},\"sem\":{\"0\":0.0},\"trial_index\":{\"0\":7}}"}, "description": null}]]}, "8": {"__type": "OrderedDict", "value": [[1558026870318, {"__type": "Data", "df": {"__type": "DataFrame", "value": "{\"arm_name\":{\"0\":\"8_0\"},\"mean\":{\"0\":1.9245392125},\"metric_name\":{\"0\":\"accuracy\"},\"sem\":{\"0\":0.0},\"trial_index\":{\"0\":8}}"}, "description": null}]]}, "9": {"__type": "OrderedDict", "value": [[1558026871567, {"__type": "Data", "df": {"__type": "DataFrame", "value": "{\"arm_name\":{\"0\":\"9_0\"},\"mean\":{\"0\":1.920448671},\"metric_name\":{\"0\":\"accuracy\"},\"sem\":{\"0\":0.0},\"trial_index\":{\"0\":9}}"}, "description": null}]]}, "10": {"__type": "OrderedDict", "value": [[1558026872188, {"__type": "Data", "df": {"__type": "DataFrame", "value": "{\"arm_name\":{\"0\":\"10_0\"},\"mean\":{\"0\":1.9219638616},\"metric_name\":{\"0\":\"accuracy\"},\"sem\":{\"0\":0.0},\"trial_index\":{\"0\":10}}"}, "description": null}]]}, "11": {"__type": "OrderedDict", "value": [[1558026872725, {"__type": "Data", "df": {"__type": "DataFrame", "value": "{\"arm_name\":{\"0\":\"11_0\"},\"mean\":{\"0\":1.9705277743},\"metric_name\":{\"0\":\"accuracy\"},\"sem\":{\"0\":0.0},\"trial_index\":{\"0\":11}}"}, "description": null}]]}, "12": {"__type": "OrderedDict", "value": [[1558026873297, {"__type": "Data", "df": {"__type": "DataFrame", "value": "{\"arm_name\":{\"0\":\"12_0\"},\"mean\":{\"0\":1.9305306482},\"metric_name\":{\"0\":\"accuracy\"},\"sem\":{\"0\":0.0},\"trial_index\":{\"0\":12}}"}, "description": null}]]}, "13": {"__type": "OrderedDict", "value": [[1558026873760, {"__type": "Data", "df": {"__type": "DataFrame", "value": "{\"arm_name\":{\"0\":\"13_0\"},\"mean\":{\"0\":1.917917032},\"metric_name\":{\"0\":\"accuracy\"},\"sem\":{\"0\":0.0},\"trial_index\":{\"0\":13}}"}, "description": null}]]}, "14": {"__type": "OrderedDict", "value": [[1558026874152, {"__type": "Data", "df": {"__type": "DataFrame", "value": "{\"arm_name\":{\"0\":\"14_0\"},\"mean\":{\"0\":1.9574336004},\"metric_name\":{\"0\":\"accuracy\"},\"sem\":{\"0\":0.0},\"trial_index\":{\"0\":14}}"}, "description": null}]]}}}